common/__init__.py
common/main.py
common/models.py
common/rest_client/__init__.py
common/rest_client/base_client.py
common/rest_client/base_client_aggregator.py
common/rest_client/base_client_camunda.py
common/rest_client/base_client_parser.py
common/rest_client/base_client_sso.py
common/rest_client/base_clients.py
common/rest_client/exceptions.py
common/utils/__init__.py
common/utils/logger.py
common/utils/utils.py
betagr_common-0.1.8.dist-info/LICENSE
betagr_common-0.1.8.dist-info/METADATA
betagr_common-0.1.8.dist-info/WHEEL
betagr_common-0.1.8.dist-info/top_level.txt
betagr_common-0.1.8.dist-info/RECORD
