Metadata-Version: 2.1
Name: betagr-common
Version: 0.1.8
Summary: API-Common package for betagr-project.
Home-page: https://github.com/AndsoiIo/betagr-common
Author: BetAgr Team
Author-email: betagr.team@gmail.com
License: UNKNOWN
Platform: UNKNOWN
Classifier: Programming Language :: Python :: 3
Classifier: License :: OSI Approved :: MIT License
Classifier: Operating System :: OS Independent
Requires-Python: >=3.6
